<?xml version="1.0" encoding="UTF-8"?>
<data xmlns="ns:workflow" xmlns:xsi="http://www.w3.org/2001/XMLSchema-instance" xsi:schemaLocation="ns:workflow resource:WorkflowData">
	<documentTypes xmlns="ns:workflow/DocumentType" xsi:schemaLocation="ns:workflow/DocumentType resource:DocumentType">
		<documentType>
			<name>IacucProtocolReferenceTypeMaintenanceDocument</name>
			<description>Create/Edit an IACUC Protocol Reference Type</description>
			<label>IACUC Protocol Reference Type</label>
			<parent>KcComplianceMaintenanceDocument</parent>
			<helpDefinitionURL>default.htm?turl=Documents/protocolreferencetype.htm</helpDefinitionURL>
		</documentType>
	</documentTypes>	
</data>