<?xml version="1.0" encoding="UTF-8"?>
<!-- Copyright 2005-2010 The Kuali Foundation.
# 
# Licensed under the Educational Community License, Version 1.0 (the "License");
# you may not use this file except in compliance with the License.
# You may obtain a copy of the License at
# 
# http://www.opensource.org/licenses/ecl1.php
# 
# Unless required by applicable law or agreed to in writing, software
# distributed under the License is distributed on an "AS IS" BASIS,
# WITHOUT WARRANTIES OR CONDITIONS OF ANY KIND, either express or implied.
# See the License for the specific language governing permissions and
# limitations under the License.
--> 

<S2SErrors>
	<!-- #RRPerformanceSite -->
	<Error>
		<MessageKey>/GrantApplication/Forms/RR_PerformanceSite/OtherSite</MessageKey>
		<Message>The maximum number of other organizations allowed is 7</Message>
		<FixLink>proposal.Organization/Location</FixLink>
	</Error>
	<Error>
		<MessageKey>/GrantApplication/Forms/RR_PerformanceSite/OtherSite/Address/State</MessageKey>
		<Message>The state code for one of the performance sites is not valid</Message>
		<FixLink>proposal.Organization/Location</FixLink>
	</Error>
	<Error>
		<MessageKey>/GrantApplication/Forms/RR_PerformanceSite/OtherSite/Address/Country</MessageKey>
		<Message>Country code is missing for one of the performance sites</Message>
		<FixLink>proposal.Organization/Location</FixLink>
	</Error>
	<Error>
		<MessageKey>/GrantApplication/Forms/RR_PerformanceSite/OtherSite/Address/Country</MessageKey>
		<Message>Country code is missing for one of the performance sites</Message>
		<FixLink>proposal</FixLink>
	</Error>
	<!-- #SF424V1_0 -->
	<Error>
		<MessageKey>/GrantApplication/Forms/GrantApplication/ApplicationTypeCode</MessageKey>
		<Message>You have a non-standard application type for the SF424.</Message>
		<FixLink>proposal</FixLink>
	</Error>
	<Error>
		<MessageKey>/GrantApplication/Forms/GrantApplication/Revision/RevisionCode1</MessageKey>
		<Message>You have entered an invalid revision type for the SF424</Message>
		<FixLink>grantsGov</FixLink>
	</Error>
	<Error>
		<MessageKey>GrantApplication/Forms/GrantApplication/ActivityTitle</MessageKey>
		<Message>Please enter the program title</Message>
		<FixLink>proposal</FixLink>
	</Error>
	<!-- #SF424V2_0 -->	
	<Error>
		<MessageKey>/GrantApplication/Forms/SF424/ApplicationTypeCode</MessageKey>
		<Message>You have a non-standard application type for the SF424</Message>
		<FixLink>proposal</FixLink>
	</Error>
	<Error>
		<MessageKey>/GrantApplication/Forms/SF424/Revision/RevisionCode1</MessageKey>
		<Message>You have entered an invalid revision type for the SF424</Message>
		<FixLink>grantsGov</FixLink>
	</Error>
	<Error>
		<MessageKey>/GrantApplication/Forms/SF424/Applicant/City</MessageKey>
		<Message>Organization's city is not valid</Message>
		<FixLink>proposal.Organization/Location</FixLink>
	</Error>
	<Error>
  		<MessageKey>/GrantApplication/Forms/SF424/PhoneNumber</MessageKey> 
  		<Message>Phone number missing for PD/PI.</Message> 
  		<FixLink>keyPersonnel</FixLink> 
  	</Error>
  	<Error>
	    <MessageKey>/GrantApplication/Forms/SF424/Email</MessageKey> 
 		<Message>Email address missing for PD/PI.</Message> 
 	    <FixLink>keyPersonnel</FixLink> 
  	</Error>  
	<!-- #SF424_Short-V1_0 -->	
	<Error>
  		<MessageKey>/GrantApplication/Forms/SF424_Short/ProjectDescription</MessageKey> 
 		<Message>Project Description required, please include a Project Summary Abstract.</Message> 
 		<FixLink>abstactsAttachments</FixLink> 
 	</Error>
 	<Error>
  		<MessageKey>/GrantApplication/Forms/SF424_Short/ProjectDirectorGroup</MessageKey> 
 		<Message>Title missing for PD/PI.</Message> 
 		<FixLink>keyPersonnel</FixLink> 
  	</Error>
  	<Error>
		<MessageKey>/GrantApplication/Forms/SF424_Short/ContactPersonGroup/Name/FirstName</MessageKey> 
 		<Message>First name missing for PD/PI.</Message> 
  		<FixLink>keyPersonnel</FixLink> 
    </Error>
    <Error>
		<MessageKey>/GrantApplication/Forms/SF424_Short/ContactPersonGroup/Name/LastName</MessageKey> 
 		<Message>Last name missing for PD/PI.</Message> 
  		<FixLink>keyPersonnel</FixLink> 
  	</Error>
  	<Error>
		<MessageKey>/GrantApplication/Forms/SF424_Short/ContactPersonGroup/Address/Street1</MessageKey> 
 		<Message>Address missing for PD/PI.</Message> 
  		<FixLink>keyPersonnel</FixLink> 
    </Error>
    <Error>
		<MessageKey>/GrantApplication/Forms/SF424_Short/ContactPersonGroup/Address/City</MessageKey> 
 		<Message>City missing for PD/PI.</Message> 
  		<FixLink>keyPersonnel</FixLink> 
    </Error>
    <Error>
		<MessageKey>/GrantApplication/Forms/SF424_Short/ContactPersonGroup/Address/Country</MessageKey> 
	    <Message>Country missing for PD/PI.</Message> 
 	    <FixLink>keyPersonnel</FixLink> 
   </Error>
	<!-- #SF424BV1_1 -->
	<Error>
		<MessageKey>/GrantApplication/Forms/Assurances/ApplicationTypeCode</MessageKey>
		<Message>You have a non-standard application type for the SF424</Message>
		<FixLink>proposal</FixLink>
	</Error>
	<Error>
		<MessageKey>/GrantApplication/Forms/Assurances/Revision/RevisionCode1</MessageKey>
		<Message>You have entered an invalid revision type for the SF424</Message>
		<FixLink>grantsGov</FixLink>
	</Error>
	<!-- #PHS398Checklist -->
	<Error>
		<MessageKey>/GrantApplication/Forms/PHS398_Checklist/FormerPDName/LastName</MessageKey>
		<Message>Last name is required for the former PD/PI</Message>
		<FixLink>questions</FixLink>
	</Error>
	<Error>
		<MessageKey>/GrantApplication/Forms/PHS398_Checklist/FormerPDName/FirstName</MessageKey>
		<Message>First name is required for the former PD/PI</Message>
		<FixLink>questions</FixLink>
	</Error>
	<Error>
		<MessageKey>/GrantApplication/Forms/PHS398_Checklist/IncomeBudgetPeriod/BudgetPeriod</MessageKey>
		<Message>You may have only 5 budget periods</Message>
		<FixLink>budgetVersions</FixLink>
	</Error>
	<Error>
		<MessageKey>/GrantApplication/Forms/PHS398_Checklist/CertificationExplanation/Certifications</MessageKey>
		<Message>Please attach a Certification Explanation for the checklist</Message>
		<FixLink>abstractsAttachments</FixLink>
	</Error>
	<!-- #NSFCoverPage -->
	<Error>
		<MessageKey>/GrantApplication/Forms/NSF_CoverPage/NSFUnitConsideration/DivisionCode</MessageKey>
		<Message>Agency division code must be specified</Message>
		<FixLink>proposal</FixLink>
	</Error>
	<Error>
		<MessageKey>/GrantApplication/Forms/NSF_CoverPage/NSFUnitConsideration/ProgramCode</MessageKey>
		<Message>Agency program code must be specified</Message>
		<FixLink>proposal</FixLink>
	</Error>
	<Error>
		<MessageKey>/GrantApplication/Forms/NSF_CoverPage/PIInfo</MessageKey>
		<Message>You must have a Principal Investigator</Message>
		<FixLink>keyPersonnel</FixLink>
	</Error>
	<Error>
		<MessageKey>/GrantApplication/Forms/NSF_CoverPage/PIInfo/DegreeType</MessageKey>
		<Message>Enter degree information for the Principal Investigator</Message>
		<FixLink>keyPersonnel</FixLink>
	</Error>
	<Error>
		<MessageKey>/GrantApplication/Forms/NSF_CoverPage/PIInfo/DegreeYear</MessageKey>
		<Message>Enter the graduation date for the Principal Investigator's highest degree</Message>
		<FixLink>keyPersonnel</FixLink>
	</Error>
	<Error>
		<MessageKey>/GrantApplication/Forms/NSF_CoverPage/FundingOpportunityNumber</MessageKey>
		<Message>Please enter the program announcement number</Message>
		<FixLink>proposal</FixLink>
	</Error>
	<!-- #ED_Abstract -->
	<Error>
		<MessageKey>/GrantApplication/Forms/AbstractAttachments/Attachments</MessageKey>
		<Message>The abstract attachment is required.</Message>
		<FixLink>abstractsAttachments</FixLink>
	</Error>
	<!-- #PHS398CoverLetter -->
	<Error>
		<MessageKey>/GrantApplication/Forms/PHS398_CoverLetter/CoverLetterFile/CoverLetterFilename</MessageKey>
		<Message>Please attach a Cover Letter.</Message>
		<FixLink>abstractsAttachments</FixLink>
	</Error>
	<!-- #RR_SF424 -->
	<Error>
		<MessageKey>/GrantApplication/Forms/RR_SF424/ApplicantInfo/OrganizationInfo/DUNSID</MessageKey>
		<Message>The selected organization does not have DUNS number</Message>
		<FixLink>proposal</FixLink>
	</Error>
	<Error>
		<MessageKey>/GrantApplication/Forms/RR_SF424/PDPIContactInfo</MessageKey>
		<Message>Contact information missing for PD/PI, please make sure a Principal Investigator has been added.</Message>
		<FixLink>keyPersonnel</FixLink>
	</Error>
	<Error>
		<MessageKey>/GrantApplication/Forms/RR_SF424/PDPIContactInfo/Address/Street1</MessageKey>
		<Message>The PI address is invalid.  Use the proposal person window to add a street address</Message>
		<FixLink>keyPersonnel</FixLink>
	</Error>
	<Error>
		<MessageKey>/GrantApplication/Forms/RR_SF424/PDPIContactInfo/Address/Country</MessageKey>
		<Message>The PI country code is invalid. Use the proposal person window to fix this</Message>
		<FixLink>keyPersonnel</FixLink>
	</Error>
	<Error>
		<MessageKey>/GrantApplication/Forms/RR_SF424/PDPIContactInfo/Address/City</MessageKey>
		<Message>The PI address is missing a city. Please use the Proposal Person window to fix this.</Message>
		<FixLink>keyPersonnel</FixLink>
	</Error>
	<Error>
		<MessageKey>/GrantApplication/Forms/RR_SF424/EstimatedProjectFunding/TotalEstimatedAmount</MessageKey>
		<Message>Total estimated amount is missing -Please provide a budget</Message>
		<FixLink>budgetVersions</FixLink>
	</Error>
	
	<Error>
		<MessageKey>/GrantApplication/Forms/RR_SF424/EstimatedProjectFunding/TotalfedNonfedrequested</MessageKey>
		<Message>Total requested funding is missing - Please provide a budget</Message>
		<FixLink>budgetVersions</FixLink>
	</Error>
	<Error>
		<MessageKey>/GrantApplication/Forms/RR_SF424/EstimatedProjectFunding/EstimatedProgramIncome</MessageKey>
		<Message>Program Income is missing - Please provide a budget</Message>
		<FixLink>budgetVersions</FixLink>
	</Error>
	<Error>
		<MessageKey>/GrantApplication/Forms/RR_SF424/ActivityTitle</MessageKey>
		<Message>Please enter the program title</Message>
		<FixLink>proposal</FixLink>
	</Error>
	<Error>
		<MessageKey>/GrantApplication/Forms/RR_SF424/AORInfo/Address/Country</MessageKey>
		<Message>The country code for the AOR is not valid for Grants.gov</Message>
		<FixLink>proposal</FixLink>
	</Error>
	<Error>
		<MessageKey>/GrantApplication/Forms/RR_SF424/AORInfo/Title</MessageKey>
		<Message>The AOR must have a title</Message>
		<FixLink>proposal</FixLink>
	</Error>
	<Error>
		<MessageKey>/GrantApplication/Forms/RR_SF424/ProjectTitle</MessageKey>
		<Message>You are missing a project title</Message>
		<FixLink>proposal</FixLink>
	</Error>
	<Error>
		<MessageKey>/GrantApplication/Forms/RR_SF424/EstimatedProjectFunding/TotalEstimatedAmount</MessageKey>
		<Message>You are missing total budget amounts</Message>
		<FixLink>budgetVersions</FixLink>
	</Error>
	<Error>
		<MessageKey>/GrantApplication/Forms/RR_SF424/EstimatedProjectFunding/TotalfedNonfedrequested</MessageKey>
		<Message>You are missing total budget amounts</Message>
		<FixLink>budgetVersions</FixLink>
	</Error>
	<Error>
		<MessageKey>/GrantApplication/Forms/RR_SF424/EstimatedProjectFunding/EstimatedProgramIncome</MessageKey>
		<Message>You are missing total budget amounts</Message>
		<FixLink>budgetVersions</FixLink>
	</Error>
	<Error>
		<MessageKey>/GrantApplication/Forms/RR_SF424/ApplicantInfo/ContactPersonInfo</MessageKey>
		<Message>You are missing a contact person for the proposal</Message>
		<FixLink>proposal</FixLink>
	</Error>

	<Error>
		<MessageKey>/GrantApplication/Forms/RR_SF424/StateID</MessageKey>
		<Message>Selected organization missing state</Message>
		<FixLink>proposal</FixLink>
	</Error>
	<Error>
		<MessageKey>/GrantApplication/Forms/RR_SF424/ApplicantInfo/OrganizationInfo/Address/City</MessageKey>
		<Message>Selected organization missing city</Message>
		<FixLink>proposal</FixLink>
	</Error>
	<Error>
		<MessageKey>/GrantApplication/Forms/RR_SF424/ApplicantInfo/OrganizationInfo/Address/County</MessageKey>
		<Message>Selected organization missing county</Message>
		<FixLink>proposal.Organization/Location</FixLink>
	</Error>
	<Error>
		<MessageKey>/GrantApplication/Forms/RR_SF424/ApplicantInfo/OrganizationInfo/Address/ZipPostalCode</MessageKey>
		<Message>Selected organization missing postal code</Message>
		<FixLink>proposal.Organization/Location</FixLink>
	</Error>
	<Error>
		<MessageKey>/GrantApplication/Forms/RR_SF424/ApplicantInfo/OrganizationInfo/Address</MessageKey>
		<Message>Selected organization missing address</Message>
		<FixLink>proposal.Organization/Location</FixLink>
	</Error>
	<Error>
		<MessageKey>/GrantApplication/Forms/RR_SF424/ApplicantInfo/ContactPersonInfo/Name/FirstName</MessageKey>
		<Message>First name missing for proposal contact person, please verify the information in the Unit Administrator table.</Message>
		<FixLink>grantsGov</FixLink>
	</Error>
	<Error>
		<MessageKey>/GrantApplication/Forms/RR_SF424/ApplicantInfo/ContactPersonInfo/Name/MiddleName</MessageKey>
		<Message>Middle name missing for contact person</Message>
		<FixLink>proposal.Organization/Location</FixLink>
	</Error>
	<Error>
		<MessageKey>/GrantApplication/Forms/RR_SF424/ApplicantInfo/ContactPersonInfo/Name/LastName</MessageKey>
		<Message>Last name missing for proposal contact person, please verify the information in the Unit Administrator table.</Message>
		<FixLink>grantsGov</FixLink>
	</Error>
	<Error>
		<MessageKey>/GrantApplication/Forms/RR_SF424/ApplicantInfo/ContactPersonInfo/Fax</MessageKey>
		<Message>Fax missing for contact person</Message>
		<FixLink>proposal.Organization/Location</FixLink>
	</Error>
	<Error>
		<MessageKey>/GrantApplication/Forms/RR_SF424/ApplicantInfo/ContactPersonInfo/Email</MessageKey>
		<Message>Email address missing for contact person</Message>
		<FixLink>proposal.Organization/Location</FixLink>
	</Error>
	<Error>
		<MessageKey>/GrantApplication/Forms/RR_SF424/ApplicantType/ApplicantTypeCode</MessageKey>
		<Message>Applicant type missing</Message>
		<FixLink>proposal.SponsorProgramInformation</FixLink>
	</Error>
	<Error>
		<MessageKey>/GrantApplication/Forms/RR_SF424/Location</MessageKey>
		<Message>Areas Affected by Project is required, please add this Abstract Type in the Abstracts and Attachments tab</Message>		
		<FixLink>abstractsAttachments</FixLink>
	</Error>
	<Error>
		<MessageKey>/GrantApplication/Forms/RR_SF424/PDPIContactInfo</MessageKey>
		<Message>PDPI contact info missing</Message>
		<FixLink>keyPersonnel</FixLink>
	</Error>
	<Error>
		<MessageKey>/GrantApplication/Forms/RR_SF424/EstimatedProjectFunding</MessageKey>
		<Message>Estimated Project funding missing</Message>
		<FixLink>budgetVersions</FixLink>
	</Error>
	<Error>
		<MessageKey>/GrantApplication/Forms/RR_SF424/AORInfo/Address</MessageKey>
		<Message>Missing AOR address</Message>
		<FixLink>proposal</FixLink>
	</Error>
	<Error>
		<MessageKey>/GrantApplication/Forms/RR_SF424/AORInfo/Phone</MessageKey>
		<Message>Missing AOR phone number</Message>
		<FixLink>proposal</FixLink>
	</Error>
	<Error>
		<MessageKey>/GrantApplication/Forms/RR_SF424/AORInfo/Fax</MessageKey>
		<Message>Missing AOR Fax</Message>
		<FixLink>proposal</FixLink>
	</Error>
	<Error>
		<MessageKey>/GrantApplication/Forms/RR_SF424/AORInfo/Email</MessageKey>
		<Message>Missing AOR email address</Message>
		<FixLink>proposal</FixLink>
	</Error>
	<Error>
		<MessageKey>/GrantApplication/Forms/RR_SF424/AORInfo/OrganizationName</MessageKey>
		<Message>Missing AOR organization name</Message>
		<FixLink>proposal</FixLink>
	</Error>

	<Error>
		<MessageKey>/GrantApplication/Forms/RR_SF424/AORInfo/DepartmentName</MessageKey>
		<Message>Missing AOR department name</Message>
		<FixLink>proposal</FixLink>
	</Error>
	<Error>
		<MessageKey>/GrantApplication/Forms/RR_SF424/AORInfo/DivisionName</MessageKey>
		<Message>Missing AOR division name</Message>
		<FixLink>proposal</FixLink>
	</Error>
	<Error>
		<MessageKey>/GrantApplication/Forms/RR_SF424/AORInfo</MessageKey>
		<Message>Missing AOR information</Message>
		<FixLink>proposal</FixLink>
	</Error>
	<Error>
 		<MessageKey>/GrantApplication/Forms/RR_SF424/ApplicantInfo/ContactPersonInfo/Phone</MessageKey>  
		<Message>Phone number missing for proposal contact person, please verify the information in the Unit Administrator table.</Message> 
	    <FixLink>grantsGov</FixLink> 
    </Error>
	<!-- #RR_SF424 V1_2 -->
	<Error>
 		<MessageKey>/GrantApplication/Forms/RR_SF424_1_2/ApplicantInfo/ContactPersonInfo/Name/FirstName</MessageKey> 
		<Message>First name missing for proposal contact person, please verify the information in the Unit Administrator table.</Message> 
 		<FixLink>grantsGov</FixLink> 
  	</Error>
  	<Error>
 		<MessageKey>/GrantApplication/Forms/RR_SF424_1_2/ApplicantInfo/ContactPersonInfo/Name/LastName</MessageKey> 
 		<Message>Last name missing for proposal contact person, please verify the information in the Unit Administrator table.</Message> 
  		<FixLink>grantsGov</FixLink> 
    </Error>
    <Error>
 		<MessageKey>/GrantApplication/Forms/RR_SF424_1_2/ApplicantInfo/ContactPersonInfo/Phone</MessageKey> 
		<Message> Phone number missing for proposal contact person, please verify the information in the Unit Administrator table.</Message> 
  		<FixLink>grantsGov</FixLink> 
  	</Error>
  	<Error>
  		<MessageKey>/GrantApplication/Forms/RR_SF424_1_2/PDPIContactInfo</MessageKey> 
 		<Message> Contact information missing for PD/PI, please make sure a Principal Investigator has been added.</Message> 
 	    <FixLink>keyPersonnel</FixLink> 
  	</Error>
	<!-- #RR_KeyPersonV1_0 -->
	<Error>
		<MessageKey>/GrantApplication/Forms/RR_KeyPerson/PDPI</MessageKey>
		<Message>A PD/PI is required, please add a Principal Investigator to the proposal.</Message>
		<FixLink>keyPersonnel</FixLink>
	</Error>
	<Error>
		<MessageKey>/GrantApplication/Forms/RR_KeyPerson/Profile/BioSketchAttached</MessageKey>
		<Message>The PI must have a BioSketch.  Upload the PDF on the Proposal Personnel screen, with "BIOSKETCH" as the description.</Message>
		<FixLink>abstractsAttachments</FixLink>
	</Error>
	<Error>
		<MessageKey>/GrantApplication/Forms/RR_KeyPerson/PDPI/Profile/Address/Country</MessageKey>
		<Message>You have entered an invalid country code for your investigator. Use the proposal person window to fix this.</Message>
		<FixLink>keyPersonnel</FixLink>
	</Error>
	<Error>
		<MessageKey>/GrantApplication/Forms/RR_KeyPerson/KeyPerson/Profile/BioSketchsAttached</MessageKey>
		<Message>Each investigator and key person must have a BioSketch.  Upload the PDF on the Proposal Personnel screen, with "BIOSKETCH" as the description.</Message>
		<FixLink>abstractsAttachments</FixLink>
	</Error>
	<!-- #RR_KeyPersonV1_1 -->
	<Error>
		<MessageKey>/GrantApplication/Forms/RR_KeyPerson/KeyPerson/Profile/BioSketchsAttached</MessageKey>
		<Message>All key persons must have a BioSketch.  Upload the PDF on the Proposal Personnel screen, with "BIOSKETCH" as the description.</Message>
		<FixLink>abstractsAttachments</FixLink>
	</Error>
	<Error>
		<MessageKey>/GrantApplication/Forms/RR_KeyPerson/PDPI/Profile/Address/Street1</MessageKey>
		<Message>The PI address is missing Address Line 1. Please use the Proposal Person window to fix this.</Message>
		<FixLink>keyPersonnel</FixLink>
	</Error>
	<Error>
		<MessageKey>/GrantApplication/Forms/RR_KeyPerson/PDPI/Profile/Address/City</MessageKey>
		<Message>The PI address is missing a city. Please use the Proposal Person window to fix this.</Message>
		<FixLink>keyPersonnel</FixLink>
	</Error>
	<Error>
		<MessageKey>/GrantApplication/Forms/RR_KeyPerson/KeyPerson/Profile/Address/City</MessageKey>
		<Message>The address for each key person must have a city. Please use the Proposal Person window to fix this.</Message>
		<FixLink>keyPersonnel</FixLink>
	</Error>
	<Error>
		<MessageKey>/GrantApplication/Forms/RR_KeyPerson/KeyPerson/Profile/Address/Street1</MessageKey>
		<Message>The address for each key person must include Address Line 1. Please use the Proposal Person window to fix this.</Message>
		<FixLink>keyPersonnel</FixLink>
	</Error>
	<Error>
 		<MessageKey>/GrantApplication/Forms/RR_KeyPerson/PDPI/Profile/BioSketchsAttached/BioSketchAttached</MessageKey> 
 		<Message>Each investigator and key person must have a BioSketch. Upload the PDF on the Personnel Attachments panel, with "BIOSKETCH" as the attachment type.</Message> 
  		<FixLink>abstractsAttachments</FixLink> 
  	</Error>
	<!-- # RR_OtherProjectInfo- -->
	<Error>
		<MessageKey>/GrantApplication/Forms/RR_OtherProjectInfo/OtherAttachments/OtherAttachment</MessageKey>
		<Message>You must have an at least one Attachment with type 'Other' or 'SupplementaryDocumentation'</Message>
		<FixLink>abstractsAttachments</FixLink>
	</Error>
	<Error>
		<MessageKey>/GrantApplication/Forms/RR_OtherProjectInfo/OtherAttachments</MessageKey>
		<Message>You must have an at least one Attachment with type 'Other' or 'SupplementaryDocumentation'</Message>
		<FixLink>abstractsAttachments</FixLink>
	</Error>
	<Error>
		<MessageKey>/GrantApplication/Forms/RR_OtherProjectInfo/AbstractAttachments</MessageKey>
		<Message>You must have a ProjectSummary with the proposal. Please attach the ProjectSummary in Abstracts and Attachments window</Message>
		<FixLink>abstractsAttachments</FixLink>
	</Error>
	<Error>
		<MessageKey>/GrantApplication/Forms/RR_OtherProjectInfo/ProjectNarrativeAttachments</MessageKey>
		<Message>You must have a Narrative with the proposal. Please attach the Narrative in Abstracts and Attachments window</Message>
		<FixLink>abstractsAttachments</FixLink>
	</Error>
	<Error>		
		<MessageKey>/GrantApplication/Forms/RR_Budget/BudgetYear1/BudgetJustificationAttachment</MessageKey>
		<Message>You must have a BudgetJustification with the proposal. Please attach the BudgetJustification in Abstracts and Attachments window</Message>
		<FixLink>abstractsAttachments</FixLink>
	</Error>
	<Error>
		<MessageKey>/GrantApplication/Forms/RR_OtherProjectInfo</MessageKey>
		<Message>RR Other Project Info form is not valid</Message>
		<FixLink>abstractsAttachments</FixLink>
	</Error>
	
	<Error>
		<MessageKey>/GrantApplication/Forms/RR_OtherProjectInfo/HumanSubjectsSupplement/ExemptionNumbers/ExemptionNumber</MessageKey>
		<Message>Valid Human Subjects exemption numbers are E1,E2,E3,E4,E5,E6</Message>
		<FixLink>specialReview</FixLink>
	</Error>
	<Error>
		<MessageKey>/GrantApplication/Forms/RR_OtherProjectInfo/ProprietaryInformationIndicator</MessageKey>
		<Message>Please answer the Proprietary Information question.</Message>
		<FixLink>questions</FixLink>
	</Error>
	<Error>
		<MessageKey>/GrantApplication/Forms/RR_OtherProjectInfo/EnvironmentalImpact</MessageKey>
		<Message>Please answer the Environmental Impact question.</Message>
		<FixLink>questions</FixLink>
	</Error>
	<Error>
		<MessageKey>/GrantApplication/Forms/RR_OtherProjectInfo/InternationalActivities</MessageKey>
		<Message>Please answer the International Activities question.</Message>
		<FixLink>questions</FixLink>
	</Error>		
	<!-- # RR_OtherProjectInfo-V1_1- -->
	<Error>
 		<MessageKey>/GrantApplication/Forms/RR_OtherProjectInfo/EnvironmentalImpact/EnvironmentalExemption/EnvironmentalExemptionExplanation</MessageKey> 
 		<Message>Please answer the Environmental Impact question.</Message> 
  		<FixLink>questions</FixLink> 
	</Error>
	<Error>
 		<MessageKey>/GrantApplication/Forms/RR_OtherProjectInfo/OtherAttachments</MessageKey> 
 		<Message>You must have an at least one Narrative with the proposal.</Message> 
  		<FixLink>abstractsAttachments</FixLink> 
	</Error>
	<!-- # RR_OtherProjectInfo-V1_2- -->
	<Error>
 		<MessageKey>/GrantApplication/Forms/RR_OtherProjectInfo_1_2/InternationalActivities</MessageKey> 
 		<Message>Please answer all required questions for this form within the Questions tab.</Message> 
  		<FixLink>questions</FixLink> 
	</Error>
	<Error>
 		<MessageKey>/GrantApplication/Forms/RR_OtherProjectInfo_1_2/ProjectSummaryAttachments</MessageKey> 
 		<Message>The ProjectSummary proposal attachment is required for this form.</Message> 
  		<FixLink>abstractsAttachments</FixLink> 
	</Error>
	<Error>
 		<MessageKey>/GrantApplication/Forms/RR_OtherProjectInfo_1_2/ProjectNarrativeAttachments</MessageKey> 
 		<Message>The Narrative proposal attachment is required for this form.</Message> 
  		<FixLink>abstractsAttachments</FixLink> 
	</Error>
	<Error>
 		<MessageKey>/GrantApplication/Forms/RR_OtherProjectInfo_1_2</MessageKey> 
 		<Message> You must include all required attachments and answer all required questions for this form.</Message> 
  		<FixLink>questions</FixLink> 
	</Error>
	<!-- # RR_OtherProjectInfo-V1_3- -->
	<Error>
 		<MessageKey>/GrantApplication/Forms/RR_OtherProjectInfo_1_3/InternationalActivities</MessageKey> 
 		<Message> Please answer all required questions for this form within the Questions tab.</Message> 
  		<FixLink>questions</FixLink> 
	</Error>
	<Error>
 		<MessageKey>/GrantApplication/Forms/RR_OtherProjectInfo_1_3/AbstractAttachments</MessageKey> 
 		<Message>The ProjectSummary proposal attachment is required for this form.</Message> 
  		<FixLink>abstractsAttachments</FixLink> 
	</Error>
	<Error>
 		<MessageKey>/GrantApplication/Forms/RR_OtherProjectInfo_1_3/ProjectNarrativeAttachments</MessageKey> 
 		<Message>The Narrative proposal attachment is required for this form.</Message> 
  		<FixLink>abstractsAttachments</FixLink> 
	</Error>
	<Error>
 		<MessageKey>/GrantApplication/Forms/RR_OtherProjectInfo_1_3</MessageKey> 
 		<Message>You  must include all required attachments and answered all required questions for this form.</Message> 
  		<FixLink>questions</FixLink> 
	</Error>	
	<!-- # RRKeyPersonExpanded- -->
	<Error>
		<MessageKey>/GrantApplication/Forms/RR_KeyPersonExpanded/KeyPerson/Profile/BioSketchsAttached</MessageKey>
		<Message>All key persons must have a BioSketch.Upload the PDF on the Proposal Personnel screen, with "BIOSKETCH" as the description.</Message>
		<FixLink>abstractsAttachments</FixLink>
	</Error>
	<Error>
		<MessageKey>/GrantApplication/Forms/RR_KeyPersonExpanded/PDPI/Profile/Address/City</MessageKey>
		<Message>The PI address is missing a city. Please use the Proposal Person window to fix this.</Message>
		<FixLink>keyPersonnel</FixLink>
	</Error>
	<Error>
		<MessageKey>/GrantApplication/Forms/RR_KeyPersonExpanded/PDPI/Profile/Address/Street1</MessageKey>
		<Message>The PI address is missing Address Line 1. Please use the Proposal Person window to fix this.</Message>
		<FixLink>keyPersonnel</FixLink>
	</Error>
	<Error>
		<MessageKey>/GrantApplication/Forms/RR_KeyPersonExpanded/KeyPerson/Profile/Address/City</MessageKey>
		<Message>The address for each key person must have a city. Please use the Proposal Person window to fix this.</Message>
		<FixLink>keyPersonnel</FixLink>
	</Error>
	<Error>
		<MessageKey>/GrantApplication/Forms/RR_KeyPersonExpanded/KeyPerson/Profile/Address/Street1</MessageKey>
		<Message>The address for each key person must include Address Line 1. Please use the Proposal Person window to fix this.</Message>
		<FixLink>keyPersonnel</FixLink>
	</Error>
	<Error>
		<MessageKey>/GrantApplication/Forms/RR_KeyPersonExpanded/KeyPerson/Profile/Email</MessageKey>
		<Message>The email address for each key person is required. Please use the Proposal Person window to fix this.</Message>
		<FixLink>keyPersonnel</FixLink>
	</Error>
	<Error>
		<MessageKey>/GrantApplication/Forms/RR_KeyPersonExpanded/KeyPerson/Profile/Phone</MessageKey>
		<Message>The phone for each key person is required. Please use the Proposal Person window to fix this.</Message>
		<FixLink>keyPersonnel</FixLink>
	</Error>
	<Error>
  		<MessageKey>/GrantApplication/Forms/RR_KeyPersonExpanded/PDPI</MessageKey> 
  		<Message>A PD/PI is required, please add a Principal Investigator to the proposal.</Message> 
  		<FixLink>keyPersonnel</FixLink> 
  	</Error>
  	<Error>
 		<MessageKey>/GrantApplication/Forms/RR_KeyPersonExpanded/PDPI/Profile/BioSketchsAttached/BioSketchAttached</MessageKey> 
 		<Message>Each investigator and key person must have a BioSketch. Upload the PDF on the Personnel Attachments panel, with "BIOSKETCH" as the attachment type.</Message> 
  		<FixLink>abstractsAttachments</FixLink> 
  	</Error>
  	<!-- # RR_KeyPersonExpanded-V1_2- -->
  	<Error>
  		<MessageKey>/GrantApplication/Forms/RR_KeyPersonExpanded_1_2/PDPI</MessageKey> 
  		<Message> A PD/PI is required, please add a Principal Investigator to the proposal.</Message> 
  		<FixLink>keyPersonnel</FixLink> 
  	</Error>
  	<Error>
  		<MessageKey>/GrantApplication/Forms/RR_KeyPersonExpanded_1_2/PDPI/Profile/BioSketchsAttached/BioSketchAttached</MessageKey> 
 		<Message>Each investigator and key person must have a BioSketch. Upload the PDF on the Personnel Attachments panel, with "BIOSKETCH" as the attachment type.</Message> 
  		<FixLink>abstractsAttachments</FixLink> 
  	</Error>  
	<!-- # Project- -->
	<Error>
		<MessageKey>/GrantApplication/Forms/ProjectNarrativeAttachments/Attachments</MessageKey>
		<Message>You must have at least one Project Narrative attachment with the proposal.</Message>
		<FixLink>abstractsAttachments</FixLink>
	</Error>
	<!-- # PHS398CoverPageSupplement- -->
	<Error>
		<MessageKey>/GrantApplication/Forms/PHS398_CoverPageSupplement/PDPI/PDPIName</MessageKey>
		<Message>You must have a Principal Investigator.</Message>
		<FixLink>keyPersonnel</FixLink>
	</Error>
	<Error>
		<MessageKey>/GrantApplication/Forms/PHS398_CoverPageSupplement/PDPI/PDPIName/LastName</MessageKey>
		<Message>Last name is required for the PD/PI.</Message>
		<FixLink>keyPersonnel</FixLink>
	</Error>
	<Error>
		<MessageKey>/GrantApplication/Forms/PHS398_CoverPageSupplement/PDPI/PDPIName/FirstName</MessageKey>
		<Message>First name is required for the PD/PI.</Message>
		<FixLink>keyPersonnel</FixLink>
	</Error>
	<Error>
		<MessageKey>/GrantApplication/Forms/PHS398_CoverPageSupplement/PDPI/IsNewInvestigator</MessageKey>
		<Message>Please answer the NIH beginning Investigator question.</Message>
		<FixLink>questions</FixLink>
	</Error>
	<Error>
		<MessageKey>/GrantApplication/Forms/PHS398_CoverPageSupplement/ContactPersonInfo/ContactName</MessageKey>
		<Message>The administrative officer for the lead unit is missing.</Message>
		<FixLink>proposal</FixLink>
	</Error>
	<Error>
		<MessageKey>/GrantApplication/Forms/PHS398_CoverPageSupplement/ContactPersonInfo/ContactName/LastName</MessageKey>
		<Message>Last name is required for the administrative contact person.</Message>
		<FixLink>proposal</FixLink>
	</Error>
	<Error>
		<MessageKey>/GrantApplication/Forms/PHS398_CoverPageSupplement/ContactPersonInfo/ContactName/FirstName</MessageKey>
		<Message>First name is required for the administrative contact person.</Message>
		<FixLink>proposal</FixLink>
	</Error>
	<Error>
		<MessageKey>/GrantApplication/Forms/PHS398_CoverPageSupplement/ContactPersonInfo/ContactPhone</MessageKey>
		<Message>Phone number is required for the administrative contact person.</Message>
		<FixLink>proposal</FixLink>
	</Error>
	<Error>
		<MessageKey>/GrantApplication/Forms/PHS398_CoverPageSupplement/ContactPersonInfo/ContactTitle</MessageKey>
		<Message>Title is required for the administrative contact person.</Message>
		<FixLink>proposal</FixLink>
	</Error>
	<Error>
		<MessageKey>/GrantApplication/Forms/PHS398_CoverPageSupplement/ContactPersonInfo/ContactAddress</MessageKey>
		<Message>Address is required for the administrative contact person.</Message>
		<FixLink>proposal</FixLink>
	</Error>
	<Error>
		<MessageKey>/GrantApplication/Forms/PHS398_CoverPageSupplement/ContactPersonInfo/ContactAddress/Street1</MessageKey>
		<Message>A valid address is required for the administrative contact person.</Message>
		<FixLink>proposal</FixLink>
	</Error>
	<Error>
		<MessageKey>/GrantApplication/Forms/PHS398_CoverPageSupplement/ContactPersonInfo/ContactAddress/City</MessageKey>
		<Message>City name is required for the contact administrative person address.</Message>
		<FixLink>proposal</FixLink>
	</Error>
	<Error>
		<MessageKey>/GrantApplication/Forms/PHS398_CoverPageSupplement/ContactPersonInfo/ContactAddress/Country</MessageKey>
		<Message>Country name is required for the administrative contact person address.</Message>
		<FixLink>proposal</FixLink>
	</Error>
	<Error>
		<MessageKey>/GrantApplication/Forms/PHS398_CoverPageSupplement/StemCells/IsHumanStemCellsInvolved</MessageKey>
		<Message>Please answer the human embryonic stem cells question.</Message>
		<FixLink>questions</FixLink>
	</Error>
	<Error>
		<MessageKey>/GrantApplication/Forms/PHS398_CoverPageSupplement/StemCells/CellLines</MessageKey>
		<Message>The registration number of the specific cell line is too long. Please see the human embryonic stem cells question for explanation.</Message>
		<FixLink>questions</FixLink>
	</Error>
	<!-- # NasaPIandAORDataSheet- -->
	<Error>
		<MessageKey>/GrantApplication/Forms/Nasa_PIandAORSupplementalDataSheet/PrincipalInvestigatorName/PDPIName</MessageKey>
		<Message>You must have a Principal Investigator.</Message>
		<FixLink>keyPersonnel</FixLink>
	</Error>
	<Error>
		<MessageKey>/GrantApplication/Forms/Nasa_PIandAORSupplementalDataSheet/PrincipalInvestigatorName/PDPIName/LastName</MessageKey>
		<Message>Last name is required for the Principal Investigator.</Message>
		<FixLink>keyPersonnel</FixLink>
	</Error>
	<Error>
		<MessageKey>/GrantApplication/Forms/Nasa_PIandAORSupplementalDataSheet/PrincipalInvestigatorName/PDPIName/FirstName</MessageKey>
		<Message>First name is required for the Principal Investigator.</Message>
		<FixLink>keyPersonnel</FixLink>
	</Error>
	<Error>
		<MessageKey>/GrantApplication/Forms/Nasa_PIandAORSupplementalDataSheet/PrincipalInvestigatorName/USGovernmentParticipation</MessageKey>
		<Message>Please answer the US government participation question.</Message>
		<FixLink>questions</FixLink>
	</Error>
	<Error>
		<MessageKey>/GrantApplication/Forms/Nasa_PIandAORSupplementalDataSheet/PrincipalInvestigatorName/InternationalParticipation</MessageKey>
		<Message>Please answer the international participation question.</Message>
		<FixLink>questions</FixLink>
	</Error>
	<Error>
		<MessageKey>budget.subaward.notfound</MessageKey>
		<Message>Subaward Budget has not been uploaded in the Budget Actions tab.</Message>
		<FixLink>budgetVersions</FixLink>
	</Error>
	<Error>
		<MessageKey>/GrantApplication/Forms/RR_Budget/BudgetYear1/Equipment/EquipmentList/EquipmentItem</MessageKey>
		<Message>A description is required for each Equipment budget line item.</Message>
		<FixLink>budgetVersions</FixLink>
	</Error>
	<!-- #RR BUDGET V1_1 -->
	<Error>
		<MessageKey>/GrantApplication/Forms/RR_Budget/BudgetYear1/KeyPersons/TotalFundForAttachedKeyPersons</MessageKey> 
 		<Message>Total funding for Key Persons not valid for Year 1</Message> 
 		<FixLink>keyPersonnel</FixLink> 
    </Error>
    <Error>
		<MessageKey>/GrantApplication/Forms/RR_Budget/BudgetYear1/KeyPersons/TotalFundForKeyPersons</MessageKey> 
 		<Message>Total funding for Key Persons not valid for Year 1, PI is required</Message> 
  		<FixLink>keyPersonnel</FixLink> 
 	</Error>
 	<Error>
		<MessageKey>/GrantApplication/Forms/RR_Budget/BudgetYear1/KeyPersons</MessageKey> 
		<Message>Key Persons for Year 1 not valid in budget</Message> 
 		<FixLink>keyPersonnel</FixLink> 
  	</Error>
  	<Error>
		<MessageKey>/GrantApplication/Forms/RR_Budget/BudgetYear2/KeyPersons/TotalFundForAttachedKeyPersons</MessageKey> 
 		<Message>Total funding for Key Persons not valid for Year 2</Message> 
  		<FixLink>keyPersonnel</FixLink> 
  	</Error>
  	<Error>
		<MessageKey>/GrantApplication/Forms/RR_Budget/BudgetYear2/KeyPersons/TotalFundForKeyPersons</MessageKey> 
		<Message>Total funding for Key Persons not valid for Year 2, PI is required</Message> 
 		<FixLink>keyPersonnel</FixLink> 
  	</Error>
  	<Error>
		<MessageKey>/GrantApplication/Forms/RR_Budget/BudgetYear2/KeyPersons</MessageKey> 
 		<Message>Key Persons for Year 2 not valid in budget</Message> 
 		<FixLink>keyPersonnel</FixLink> 
 	</Error>
 	<Error>
		<MessageKey>/GrantApplication/Forms/RR_Budget/BudgetYear3/KeyPersons/TotalFundForAttachedKeyPersons</MessageKey> 
		<Message>Total funding for Key Persons not valid for Year 3</Message> 
  		<FixLink>keyPersonnel</FixLink> 
  	</Error>
  	<Error>
		<MessageKey>/GrantApplication/Forms/RR_Budget/BudgetYear3/KeyPersons/TotalFundForKeyPersons</MessageKey> 
		<Message>Total funding for Key Persons not valid for Year 3, PI is required</Message> 
 		<FixLink>keyPersonnel</FixLink> 
  	</Error>
  	<Error>
		<MessageKey>/GrantApplication/Forms/RR_Budget/BudgetYear3/KeyPersons</MessageKey> 
 		<Message>Key Persons for Year 3 not valid in budget</Message> 
  		<FixLink>keyPersonnel</FixLink> 
  	</Error>
  	<Error>
		<MessageKey>/GrantApplication/Forms/RR_Budget/BudgetYear4/KeyPersons/TotalFundForAttachedKeyPersons</MessageKey> 
 		<Message>Total funding for Key Persons not valid for Year 4</Message> 
 		<FixLink>keyPersonnel</FixLink> 
 	</Error>
  	<Error>
		<MessageKey>/GrantApplication/Forms/RR_Budget/BudgetYear4/KeyPersons/TotalFundForKeyPersons</MessageKey> 
		<Message>Total funding for Key Persons not valid for Year 4, PI is required</Message> 
  		<FixLink>keyPersonnel</FixLink> 
 	</Error>
 	<Error>
		<MessageKey>/GrantApplication/Forms/RR_Budget/BudgetYear4/KeyPersons</MessageKey> 
		<Message>Key Persons for Year 4 not valid in budget</Message> 
  		<FixLink>keyPersonnel</FixLink> 
  	</Error>
  	<Error>
		<MessageKey>/GrantApplication/Forms/RR_Budget/BudgetYear5/KeyPersons/TotalFundForAttachedKeyPersons</MessageKey> 
 		<Message>Total funding for Key Persons not valid for Year 5</Message> 
  		<FixLink>keyPersonnel</FixLink> 
  	</Error>
  	<Error>
		<MessageKey>/GrantApplication/Forms/RR_Budget/BudgetYear5/KeyPersons/TotalFundForKeyPersons</MessageKey> 
 		<Message>Total funding for Key Persons not valid for Year 5, PI is required</Message> 
  		<FixLink>keyPersonnel</FixLink> 
 	</Error>
 	<Error>
		<MessageKey>/GrantApplication/Forms/RR_Budget/BudgetYear5/KeyPersons</MessageKey> 
 		<Message>Key Persons for Year 5 not valid in budget</Message> 
  		<FixLink>keyPersonnel</FixLink> 
  	</Error>
  	<Error>
 		<MessageKey>/GrantApplication/Forms/RR_Budget/BudgetYear1</MessageKey> 
 		<Message>Please add a budget to the proposal.</Message> 
 		<FixLink>budgetVersions</FixLink> 
  	</Error>
  	<Error>
 	    <MessageKey>/GrantApplication/Forms/RR_Budget/BudgetYear1/Equipment/EquipmentList/EquipmentItem</MessageKey> 
  		<Message>A description is required for each Equipment budget line item.</Message> 
  		<FixLink>budgetVersions</FixLink> 
    </Error> 	
    <!-- #RR BUDGET10 V1_1 -->
    <Error>
 		<MessageKey>/GrantApplication/Forms/RR_Budget10/BudgetYear/KeyPersons/TotalFundForAttachedKeyPersons</MessageKey> 
  		<Message>Total funding for Key Persons not valid</Message> 
  		<FixLink>keyPersonnel</FixLink> 
  	</Error>
  	<Error>
 		<MessageKey>/GrantApplication/Forms/RR_Budget10/BudgetYear/KeyPersons/TotalFundForKeyPersons</MessageKey> 
  		<Message>Total funding for Key Persons not valid, PI is required.</Message> 
  		<FixLink>keyPersonnel</FixLink> 
 	</Error>
 	<Error>
 		<MessageKey>/GrantApplication/Forms/RR_Budget10/BudgetYear/KeyPersons</MessageKey> 
  		<Message>Key Persons not valid in budget.</Message> 
  		<FixLink>keyPersonnel</FixLink> 
 	</Error>
 	<Error>
 		<MessageKey>/GrantApplication/Forms/RR_Budget10/BudgetJustificationAttachment</MessageKey> 
  		<Message>You must have a BudgetJustification with the proposal. Please attach the BudgetJustification in Abstracts and Attachments window</Message> 
  		<FixLink>abstractsAttachments</FixLink> 
  	</Error>
  	<Error>
 		<MessageKey>/GrantApplication/Forms/RR_Budget10/BudgetYear/Equipment/EquipmentList/EquipmentItem</MessageKey> 
  		<Message>A description is required for each Equipment budget line item.</Message> 
  		<FixLink>budgetVersions</FixLink> 
 	</Error> 
 	<!-- #RR FedNonFedBudget V1_1 -->
 	<Error>
  		<MessageKey>/GrantApplication/Forms/RR_FedNonFedBudget/BudgetSummary</MessageKey> 
  		<Message>There is no budget summary information please add a budget to the proposal.</Message> 
  		<FixLink>budgetVersions</FixLink> 
  	</Error>
  	<Error>
  		<MessageKey>/GrantApplication/Forms/RR_FedNonFedBudget</MessageKey> 
 		<Message>Please add a budget to the proposal.</Message> 
  		<FixLink>budgetVersions</FixLink> 
  	</Error>
  	<Error>
 		<MessageKey>/GrantApplication/Forms/RR_FedNonFedBudget/BudgetYear1/Equipment/EquipmentList/EquipmentItem</MessageKey> 
  		<Message>A description is required for each Equipment budget line item.</Message> 
  		<FixLink>budgetVersions</FixLink> 
  	</Error>
  	<Error>
		<MessageKey>/GrantApplication/Forms/RR_FedNonFedBudget/BudgetYear1/KeyPersons/TotalFundForAttachedKeyPersons</MessageKey> 
 		<Message>Total funding for Key Persons not valid for Year 1</Message> 
  		<FixLink>keyPersonnel</FixLink> 
  	</Error>
  	<Error>
 		<MessageKey>/GrantApplication/Forms/RR_FedNonFedBudgetBudgetYear1/KeyPersons/TotalFundForKeyPersons</MessageKey> 
 		<Message>Total funding for Key Persons not valid for Year 1, PI is required</Message> 
 		<FixLink>keyPersonnel</FixLink> 
  	</Error>
  	<Error>
  		<MessageKey>/GrantApplication/Forms/RR_FedNonFedBudget/BudgetYear1/KeyPersons</MessageKey> 
  		<Message>Key Persons for Year 1 not valid in budget</Message> 
  		<FixLink>keyPersonnel</FixLink> 
  	</Error>
  	<Error>
		<MessageKey>/GrantApplication/Forms/RR_FedNonFedBudget/BudgetYear2/KeyPersons/TotalFundForAttachedKeyPersons</MessageKey> 
 		<Message>Total funding for Key Persons not valid for Year 2</Message> 
  		<FixLink>keyPersonnel</FixLink> 
  	</Error>
  	<Error>
		<MessageKey>/GrantApplication/Forms/RR_FedNonFedBudget/BudgetYear2/KeyPersons/TotalFundForKeyPersons</MessageKey> 
 		<Message>Total funding for Key Persons not valid for Year 2, PI is required</Message> 
  		<FixLink>keyPersonnel</FixLink> 
  	</Error>
  	<Error>
		<MessageKey>/GrantApplication/Forms/RR_FedNonFedBudget/BudgetYear2/KeyPersons</MessageKey> 
 		<Message>Key Persons for Year 2 not valid in budget</Message> 
  		<FixLink>keyPersonnel</FixLink> 
  	</Error>
  	<Error>
		<MessageKey>/GrantApplication/Forms/RR_FedNonFedBudget/BudgetYear3/KeyPersons/TotalFundForAttachedKeyPersons</MessageKey> 
 		<Message>Total funding for Key Persons not valid for Year 3</Message> 
  		<FixLink>keyPersonnel</FixLink> 
 	</Error>
 	<Error>
		<MessageKey>/GrantApplication/Forms/RR_FedNonFedBudget/BudgetYear3/KeyPersons/TotalFundForKeyPersons</MessageKey> 
 		<Message>Total funding for Key Persons not valid for Year 3, PI is required</Message> 
  		<FixLink>keyPersonnel</FixLink> 
  	</Error>
  	<Error>
		<MessageKey>/GrantApplication/Forms/RR_FedNonFedBudget/BudgetYear3/KeyPersons</MessageKey>
 		<Message>Key Persons for Year 3 not valid in budget</Message> 
  		<FixLink>keyPersonnel</FixLink> 
  	</Error>
  	<Error>
		<MessageKey>/GrantApplication/Forms/RR_FedNonFedBudget/BudgetYear4/KeyPersons/TotalFundForAttachedKeyPersons</MessageKey> 
 		<Message>Total funding for Key Persons not valid for Year 4</Message> 
  		<FixLink>keyPersonnel</FixLink> 
  	</Error>
  	<Error>
		<MessageKey>/GrantApplication/Forms/RR_FedNonFedBudget/BudgetYear4/KeyPersons/TotalFundForKeyPersons</MessageKey> 
 		<Message>Total funding for Key Persons not valid for Year 4, PI is required</Message> 
  		<FixLink>keyPersonnel</FixLink> 
  	</Error>
  	<Error>
		<MessageKey>/GrantApplication/Forms/RR_FedNonFedBudget/BudgetYear4/KeyPersons</MessageKey> 
 		<Message>Key Persons for Year 4 not valid in budget</Message> 
  		<FixLink>keyPersonnel</FixLink> 
  	</Error>
  	<Error>
		<MessageKey>/GrantApplication/Forms/RR_FedNonFedBudget/BudgetYear5/KeyPersons/TotalFundForAttachedKeyPersons</MessageKey> 
 		<Message>Total funding for Key Persons not valid for Year 5</Message> 
  		<FixLink>keyPersonnel</FixLink> 
  	</Error>
  	<Error>
		<MessageKey>/GrantApplication/Forms/RR_FedNonFedBudget/BudgetYear5/KeyPersons/TotalFundForKeyPersons</MessageKey> 
 		<Message>Total funding for Key Persons not valid for Year 5, PI is required</Message> 
  		<FixLink>keyPersonnel</FixLink> 
  	</Error>
  	<Error>
		<MessageKey>/GrantApplication/Forms/RR_FedNonFedBudget/BudgetYear5/KeyPersons</MessageKey> 
 		<Message>Key Persons for Year 5 not valid in budget</Message> 
  		<FixLink>keyPersonnel</FixLink> 
  	</Error>
  	<!-- #RR FedNonFedBudget10 V1_1 -->
  	<Error>
 		<MessageKey>/GrantApplication/Forms/RR_FedNonFedBudget10/BudgetSummary</MessageKey> 
  		<Message>There is no budget summary information please add a budget to the proposal.</Message> 
  		<FixLink>budgetVersions</FixLink> 
  	</Error>
  	<Error>
  		<MessageKey>/GrantApplication/Forms/RR_FedNonFedBudget10</MessageKey> 
  		<Message>Please add a budget to the proposal.</Message> 
  		<FixLink>budgetVersions</FixLink> 
  	</Error>
  	<Error> 
  		<MessageKey>/GrantApplication/Forms/RR_FedNonFedBudget10/BudgetJustificationAttachment</MessageKey> 
  		<Message>A budget justification is required; please add one in Proposal Attachments</Message> 
  		<FixLink>abstactsAttachments</FixLink> 
  	</Error>
  	<Error>
 		<MessageKey>/GrantApplication/Forms/RR_FedNonFedBudget10/BudgetYear/Equipment/EquipmentList/EquipmentItem</MessageKey> 
  		<Message>A description is required for each Equipment budget line item.</Message> 
  		<FixLink>budgetVersions</FixLink> 
  	</Error>
  	<Error>
 		<MessageKey>/GrantApplication/Forms/RR_FedNonFedBudget10/BudgetYear/KeyPersons/TotalFundForAttachedKeyPersons</MessageKey> 
  		<Message>Total funding for Key Persons not valid</Message> 
  		<FixLink>keyPersonnel</FixLink> 
  	</Error>
  	<Error>
 		<MessageKey>/GrantApplication/Forms/RR_FedNonFedBudget10/BudgetYear/KeyPersons/TotalFundForKeyPersons</MessageKey> 
  		<Message>Total funding for Key Persons not valid, PI is required.</Message> 
  		<FixLink>keyPersonnel</FixLink> 
  	</Error>
  	<Error>
 		<MessageKey>/GrantApplication/Forms/RR_FedNonFedBudget10/BudgetYear/KeyPersons</MessageKey> 
  		<Message>Key Persons not valid in budget.</Message> 
  		<FixLink>keyPersonnel</FixLink>
  	</Error>
  	<!-- #RR_PersonalData-V1_1 -->
  	<Error>
 		<MessageKey>/GrantApplication/Forms/RR_PersonalData/ProjectDirector</MessageKey> 
 		<Message> A PD/PI is required, please add a Principal Investigator to the proposal.</Message> 
  		<FixLink>keyPersonnel</FixLink> 
	</Error>
	<!-- #RR_PersonalData_1_2-V1_2-->
	<Error>
 		<MessageKey>/GrantApplication/Forms/RR_PersonalData_1_2/ProjectDirector</MessageKey> 
 		<Message> A PD/PI is required, please add a Principal Investigator to the proposal.</Message> 
  		<FixLink>keyPersonnel</FixLink> 
	</Error>
	<!-- #NASA_OtherProjectInformation-V1_0-->
	<Error>
		<MessageKey>/GrantApplication/Forms/NASA_OtherProjectInformation/HistoricImpact/HistoricImpactQ</MessageKey> 
 		<Message>Please answer the Historical Sites question.</Message> 
  		<FixLink>questions</FixLink> 
	</Error>
	<!-- #NASA_SeniorKeyPersonSupplementalDataSheet-V1_0-->
	<Error>
 		<MessageKey>/GrantApplication/Forms/NASA_SeniorKeyPersonSupplementalDataSheet/Senior_Key_Person</MessageKey> 
 		<Message>At least one Co-Investigator or Key Person is required for this form.</Message> 
  		<FixLink>keyPersonnel</FixLink> 
	</Error>
	<!-- #PHS398_CoverLetter-V1_1-->
	<Error>
 		<MessageKey>/GrantApplication/Forms/PHS398_CoverLetter</MessageKey> 
 		<Message>Please attach a Cover Letter.</Message> 
  		<FixLink>abstractsAttachments</FixLink> 
	</Error>
	<!-- #PHS398_CoverLetter-V1_2-->	
	<Error>
 		<MessageKey>/GrantApplication/Forms/PHS_CoverLetter_1_2/CoverLetterFile</MessageKey> 
 		<Message>Please attach a Cover Letter.</Message> 
  		<FixLink>abstractsAttachments</FixLink> 
	</Error>
	<!-- #PHS398_Checklist V1_3-->
	<Error>
 		<MessageKey>/GrantApplication/Forms/PHS398_Checklist_1_3/DisclosurePermission</MessageKey> 
 		<Message>PI is required</Message> 
  		<FixLink>abstractsAttachments</FixLink> 
	</Error>
	<!-- #PHS398_CoverPageSupplement-V1_3-->
	<Error>
 		<MessageKey>/GrantApplication/Forms/PHS398_CoverPageSupplement_1_3/ContactPersonInfo/ContactName/FirstName</MessageKey> 
 		<Message>First name missing for contact person.</Message> 
  		<FixLink>keyPersonnel</FixLink> 
	</Error>
	<Error>
 		<MessageKey>/GrantApplication/Forms/PHS398_CoverPageSupplement_1_3/ContactPersonInfo/ContactName/LastName</MessageKey> 
 		<Message>Last name missing for contact person.</Message> 
  		<FixLink>keyPersonnel</FixLink> 
	</Error>
	<Error>
 		<MessageKey>/GrantApplication/Forms/PHS398_CoverPageSupplement_1_3/ContactPersonInfo/ContactPhone</MessageKey> 
 		<Message>Phone number missing for contact person.</Message> 
  		<FixLink>keyPersonnel</FixLink> 
	</Error>
	<Error>
 		<MessageKey>/GrantApplication/Forms/PHS398_CoverPageSupplement_1_3/ContactPersonInfo/ContactTitle</MessageKey> 
 		<Message>Title missing for contact person.</Message> 
  		<FixLink>keyPersonnel</FixLink> 
	</Error>
	<Error>
 		<MessageKey>/GrantApplication/Forms/PHS398_CoverPageSupplement_1_3/ContactPersonInfo/ContactAddress/Street1</MessageKey> 
 		<Message>Address missing for contact person.</Message> 
  		<FixLink>keyPersonnel</FixLink> 
	</Error>
	<Error>
 		<MessageKey>/GrantApplication/Forms/PHS398_CoverPageSupplement_1_3/ContactPersonInfo/ContactAddress/City</MessageKey> 
 		<Message>City missing for contact person.</Message> 
  		<FixLink>keyPersonnel</FixLink> 
	</Error>
	<Error>
 		<MessageKey>/GrantApplication/Forms/PHS398_CoverPageSupplement_1_3/ContactPersonInfo/ContactAddress/Country</MessageKey> 
 		<Message>Country missing for contact person.</Message> 
  		<FixLink>keyPersonnel</FixLink> 
	</Error>	
	<Error>
 		<MessageKey>/GrantApplication/Forms/PHS398_CoverPageSupplement_1_3/PDPI/PDPIName</MessageKey> 
 		<Message>You must have a Principal Investigator.</Message> 
  		<FixLink>keyPersonnel</FixLink> 
	</Error>
	<Error>
 		<MessageKey>/GrantApplication/Forms/PHS398_CoverPageSupplement_1_3/StemCells/isHumanStemCellsInvolved</MessageKey> 
 		<Message>Please answer the Stem Cells question.</Message> 
  		<FixLink>questions</FixLink> 
	</Error>	
	<!-- #PHS398_CoverPageSupplement-V1_4-->
	<Error>
 		<MessageKey>/GrantApplication/Forms/PHS398_CoverPageSupplement_1_4/PDPI/PDPIName</MessageKey> 
 		<Message>You must have a Principal Investigator.</Message> 
  		<FixLink>keyPersonnel</FixLink> 
	</Error>	
	<Error>
 		<MessageKey>/GrantApplication/Forms/PHS398_CoverPageSupplement_1_4/ContactPersonInfo/ContactName/FirstName</MessageKey> 
 		<Message>First name missing for proposal contact person, please verify the information in the Unit Administrator table.</Message> 
  		<FixLink>grantsGov</FixLink> 
	</Error>
	<Error>
 		<MessageKey>/GrantApplication/Forms/PHS398_CoverPageSupplement_1_4/ContactPersonInfo/ContactName/LastName</MessageKey> 
 		<Message>Last name missing for proposal contact person, please verify the information in the Unit Administrator table.</Message> 
  		<FixLink>grantsGov</FixLink> 
	</Error>
	<Error>
 		<MessageKey>/GrantApplication/Forms/PHS398_CoverPageSupplement_1_4/ContactPersonInfo/ContactPhone</MessageKey> 
 		<Message>Phone number missing for contact person, please verify the information in the Unit Administrator table.</Message> 
  		<FixLink>grantsGov</FixLink> 
	</Error>
	<Error>
 		<MessageKey>/GrantApplication/Forms/PHS398_CoverPageSupplement_1_4/ContactPersonInfo/ContactTitle</MessageKey> 
 		<Message>Title missing for contact person, please verify the information in the Unit Administrator table.</Message> 
  		<FixLink>grantsGov</FixLink> 
	</Error>
	<Error>
 		<MessageKey>/GrantApplication/Forms/PHS398_CoverPageSupplement_1_4/ContactPersonInfo/ContactAddress/Street1</MessageKey> 
 		<Message>Address missing for contact person, please verify the information in the Unit Administrator table.</Message> 
  		<FixLink>grantsGov</FixLink> 
	</Error>
	<Error>
 		<MessageKey>/GrantApplication/Forms/PHS398_CoverPageSupplement_1_4/ContactPersonInfo/ContactAddress/City</MessageKey> 
 		<Message>City missing for contact person, please verify the information in the Unit Administrator table.</Message> 
  		<FixLink>grantsGov</FixLink> 
	</Error>
	<Error>
 		<MessageKey>/GrantApplication/Forms/PHS398_CoverPageSupplement_1_4/ContactPersonInfo/ContactAddress/Country</MessageKey> 
 		<Message>Country missing for contact person, please verify the information in the Unit Administrator table.</Message> 
  		<FixLink>grantsGov</FixLink> 
	</Error>
	<Error>
 		<MessageKey>/GrantApplication/Forms/PHS398_CoverPageSupplement_1_4/StemCells/isHumanStemCellsInvolved</MessageKey> 
 		<Message>Please answer the Stem Cells question.</Message> 
  		<FixLink>questions</FixLink> 
	</Error>
	<!-- #PHS398_ModularBudget-V1_1-->
	<Error>
 		<MessageKey>/GrantApplication/Forms/PHS398_ModularBudget</MessageKey> 
 		<Message>Please add a budget to the proposal and complete the Modular Budget tab.</Message> 
  		<FixLink>budgetVersions</FixLink> 
	</Error>
	<!-- #Budget-V1_1-->
	<Error>
 		<MessageKey>/GrantApplication/Forms/BudgetNarrativeAttachments/Attachments</MessageKey> 
 		<Message>Please attach a Budget Attachment file.</Message> 
  		<FixLink>abstractsAttachments</FixLink> 
	</Error>
	<!-- #Other-->
	<Error>
 		<MessageKey>/GrantApplication/Forms/OtherNarrativeAttachments/Attachments</MessageKey> 
 		<Message>Please attach an Other Attachments file.</Message> 
  		<FixLink>abstractsAttachments</FixLink> 
	</Error>
	<!-- #ED524_Budget-V1_1-->
	<Error>
 		<MessageKey>/GrantApplication/Forms</MessageKey> 
 		<Message>Please add a budget to the proposal.</Message> 
  		<FixLink>budgetVersions</FixLink> 
	</Error>
	<!-- #ED_SF424_Supplement-V1_1-->
	<Error>
 		<MessageKey>/GrantApplication/Forms/ED_SF424_Supplement/ProjectDirector</MessageKey> 
 		<Message>You must have a Project Director/Principal Investigator.</Message> 
  		<FixLink>keyPersonnel</FixLink> 
	</Error>
	<!-- #PHS398_CareerDevelopmentAwardSup_1_1-V1_1-->
	<Error>
 		<MessageKey>/GrantApplication/Forms/PHS398_CareerDevelopmentAwardSup_1_1/CareerDevelopmentAwardAttachments/Appendix</MessageKey> 
 		<Message>Career Research Strategy attachment is required.</Message> 
  		<FixLink>abstractsAttachments</FixLink> 
	</Error>
	<Error>
 		<MessageKey>/GrantApplication/Forms/PHS398_CareerDevelopmentAwardSup_1_1/CareerDevelopmentAwardAttachments</MessageKey> 
 		<Message>PHS398_CareerDevelopmentAwardSup_1_1-V1.1 is not valid, missing required attachment.</Message> 
  		<FixLink>abstractsAttachments</FixLink> 
	</Error>
	<!-- #PHS398_ResearchPlan V1_3-->
	<Error>
 		<MessageKey>/GrantApplication/Forms/PHS398_ResearchPlan_1_3/ResearchPlanAttachments/ResearchStrategy</MessageKey> 
 		<Message>Research Strategy attachment is required for Research Plan.</Message> 
  		<FixLink>abstractsAttachments</FixLink> 
	</Error>
	<!-- #PerformanceSite V1_3-->
	<Error>
 		<MessageKey>/GrantApplication/Forms/PerformanceSite_1_3/AttachedFile</MessageKey> 
 		<Message>Performance Sites attachment is required since Performance Site Locations exceed the maximum of 29.</Message> 
  		<FixLink>abstractsAttachments</FixLink> 
	</Error>
	<!-- #PerformanceSite V1_4-->
	<Error>
 		<MessageKey>/GrantApplication/Forms/PerformanceSite_1_4/AttachedFile</MessageKey> 
 		<Message>Performance Sites attachment is required since Performance Site Locations exceed the maximum of 29.</Message> 
  		<FixLink>abstractsAttachments</FixLink> 
	</Error>
	<!-- #PHS_Fellowship_Supplemental V1_1-->
	<Error>
 		<MessageKey>/GrantApplication/Forms/PHS_Fellowship_Supplemental_1_1/ResearchTrainingPlan/HumanSubjectsInvolved</MessageKey> 
 		<Message>Human Subjects Involved is not valid, please answer all required questions for this form within the Questions tab.</Message> 
  		<FixLink>questions</FixLink> 
	</Error>
	<Error>
 		<MessageKey>/GrantApplication/Forms/PHS_Fellowship_Supplemental_1_1/ResearchTrainingPlan/HumanSubjectsIndefinite</MessageKey> 
 		<Message>Human Subjects Indefinite is not valid, please answer all required questions for this form within the Questions tab.</Message> 
  		<FixLink>questions</FixLink> 
	</Error>
	<Error>
 		<MessageKey>/GrantApplication/Forms/PHS_Fellowship_Supplemental_1_1/ResearchTrainingPlan/ClinicalTrial</MessageKey> 
 		<Message>Clinical Trial response is not valid, please answer all required questions for this form within the Questions tab.</Message> 
  		<FixLink>questions</FixLink> 
	</Error>
	<Error>
 		<MessageKey>/GrantApplication/Forms/PHS_Fellowship_Supplemental_1_1/ResearchTrainingPlan/Phase3ClinicalTrial</MessageKey> 
 		<Message>Phase 3 Clinical Trial response is not valid, please answer all required questions for this form within the Questions tab.</Message> 
  		<FixLink>questions</FixLink> 
	</Error>
	<Error>
 		<MessageKey>/GrantApplication/Forms/PHS_Fellowship_Supplemental_1_1/ResearchTrainingPlan/VertebrateAnimalsUsed</MessageKey> 
 		<Message>Vertebrate Animals Used is not valid, please answer all required questions for this form within the Questions tab.</Message> 
  		<FixLink>questions</FixLink> 
	</Error>
	<Error>
 		<MessageKey>/GrantApplication/Forms/PHS_Fellowship_Supplemental_1_1/ResearchTrainingPlan/VertebrateAnimalsIndefinite</MessageKey> 
 		<Message>Vertebrate Animals Indefinite is not valid, please answer all required questions for this form within the Questions tab.</Message> 
  		<FixLink>questions</FixLink> 
	</Error>
	<Error>
 		<MessageKey>/GrantApplication/Forms/PHS_Fellowship_Supplemental_1_1/ResearchTrainingPlan</MessageKey> 
 		<Message>Please answer all required questions and include all required attachments for this form.</Message> 
  		<FixLink>questions</FixLink> 
	</Error>
	<Error>
 		<MessageKey>/GrantApplication/Forms/PHS_Fellowship_Supplemental_1_1/AdditionalInformation/Citizenship</MessageKey> 
 		<Message>Citizenship is not valid for PI, please make sure a PI has been added and that person has a valid citizenship type indicated.</Message> 
  		<FixLink>keyPersonnel</FixLink> 
	</Error>
	<Error>
 		<MessageKey>/GrantApplication/Forms/PHS_Fellowship_Supplemental_1_1/AdditionalInformation/ChangeOfInstitution</MessageKey> 
 		<Message>Change of Institution is not valid, please answer all required questions for this form within the Questions tab.</Message> 
  		<FixLink>questions</FixLink> 
	</Error>
	<Error>
 		<MessageKey>/GrantApplication/Forms/PHS_Fellowship_Supplemental_1_1/AdditionalInformation</MessageKey> 
 		<Message>Additional information is not valid, please answer all required questions for this form within the Questions tab.</Message> 
  		<FixLink>questions</FixLink> 
	</Error>
	<Error>
 		<MessageKey>/GrantApplication/Forms/PHS_Fellowship_Supplemental_1_1/Budget/FederalStipendRequested</MessageKey> 
 		<Message>Stipend Requested is not valid, please make sure a budget has been added.</Message> 
  		<FixLink>budgetVersions</FixLink> 
	</Error>
	<!-- #PHS_Fellowship_Supplemental V1_2-->	
	<Error>
 		<MessageKey>/GrantApplication/Forms/PHS_Fellowship_Supplemental_1_2/ResearchTrainingPlan/HumanSubjectsInvolved</MessageKey> 
 		<Message>Human Subjects Involved is not valid, please answer all required questions for this form within the Questions tab.</Message> 
  		<FixLink>questions</FixLink> 
	</Error>
	<Error>
 		<MessageKey>/GrantApplication/Forms/PHS_Fellowship_Supplemental_1_2/ResearchTrainingPlan/HumanSubjectsIndefinite</MessageKey> 
 		<Message>Human Subjects Indefinite is not valid, please answer all required questions for this form within the Questions tab.</Message> 
  		<FixLink>questions</FixLink> 
	</Error>
	<Error>
 		<MessageKey>/GrantApplication/Forms/PHS_Fellowship_Supplemental_1_2/ResearchTrainingPlan/ClinicalTrial</MessageKey> 
 		<Message>Clinical Trial response is not valid, please answer all required questions for this form within the Questions tab.</Message> 
  		<FixLink>questions</FixLink> 
	</Error>
	<Error>
 		<MessageKey>/GrantApplication/Forms/PHS_Fellowship_Supplemental_1_2/ResearchTrainingPlan/Phase3ClinicalTrial</MessageKey> 
 		<Message>Phase 3 Clinical Trial response is not valid, please answer all required questions for this form within the Questions tab.</Message> 
  		<FixLink>questions</FixLink> 
	</Error>
	<Error>
 		<MessageKey>/GrantApplication/Forms/PHS_Fellowship_Supplemental_1_2/ResearchTrainingPlan/VertebrateAnimalsUsed</MessageKey> 
 		<Message>Vertebrate Animals Used is not valid, please answer all required questions for this form within the Questions tab.</Message> 
  		<FixLink>questions</FixLink> 
	</Error>
	<Error>
 		<MessageKey>/GrantApplication/Forms/PHS_Fellowship_Supplemental_1_2/ResearchTrainingPlan/VertebrateAnimalsIndefinite</MessageKey> 
 		<Message>Vertebrate Animals Indefinite, please answer all required questions for this form within the Questions tab.</Message> 
  		<FixLink>questions</FixLink> 
	</Error>
	<Error>
 		<MessageKey>/GrantApplication/Forms/PHS_Fellowship_Supplemental_1_2/ResearchTrainingPlan</MessageKey> 
 		<Message>Please answer all required questions and include all required attachments for this form.</Message> 
  		<FixLink>questions</FixLink> 
	</Error>
	<Error>
 		<MessageKey>/GrantApplication/Forms/PHS_Fellowship_Supplemental_1_2/AdditionalInformation/StemCells</MessageKey> 
 		<Message>Stem Cells response, please answer all required questions for this form within the Questions tab.</Message> 
  		<FixLink>questions</FixLink> 
	</Error>
	<Error>
 		<MessageKey>/GrantApplication/Forms/PHS_Fellowship_Supplemental_1_2/AdditionalInformation/CurrentPriorNRSASupportIndicator</MessageKey> 
 		<Message>Current &amp; Prior NRSA support response is not valid, please answer all required questions for this form within the Questions tab.</Message> 
  		<FixLink>questions</FixLink> 
	</Error>
	<Error>
 		<MessageKey>/GrantApplication/Forms/PHS_Fellowship_Supplemental_1_2/AdditionalInformation/ConcurrentSupport</MessageKey> 
 		<Message>Concurrent support response is not valid, please answer all required questions for this form within the Questions tab.</Message> 
  		<FixLink>questions</FixLink> 
	</Error>
	<Error>
 		<MessageKey>/GrantApplication/Forms/PHS_Fellowship_Supplemental_1_2/AdditionalInformation/Citizenship</MessageKey> 
 		<Message>Citizenship is not valid for PI, please make sure a PI has been added and that person has a valid citizenship type indicated.</Message> 
  		<FixLink>keyPersonnel</FixLink> 
	</Error>
	<Error>
 		<MessageKey>/GrantApplication/Forms/PHS_Fellowship_Supplemental_1_2/AdditionalInformation</MessageKey> 
 		<Message>Additional information is not valid, please answer all required questions for this form within the Questions tab.</Message> 
  		<FixLink>questions</FixLink> 
	</Error>
	<Error>
 		<MessageKey>/GrantApplication/Forms/PHS_Fellowship_Supplemental_1_2/Sponsors</MessageKey> 
 		<Message>Sponsors is not valid, please make sure the appropriate attachments and questions have been answered.</Message> 
  		<FixLink>abstractsAttachments</FixLink> 
	</Error>
	<!-- #NSF_CoverPage_1_3-V1_3-->
	<Error>
 		<MessageKey>/GrantApplication/Forms/NSF_CoverPage_1_3/NSFUnitConsideration/DivisionCode</MessageKey> 
 		<Message>Sponsor Division Code is required (must be at least 8 characters)</Message> 
  		<FixLink>proposal</FixLink> 
	</Error>
	<Error>
 		<MessageKey>/GrantApplication/Forms/NSF_CoverPage_1_3/NSFUnitConsideration/ProgramCode</MessageKey> 
 		<Message>Sponsor Program Code is required (must be at least 4 characters)</Message> 
  		<FixLink>proposal</FixLink> 
	</Error>
	<!-- #PHS398_TrainingBudget-V1_0-->
	<Error>
 		<MessageKey>/GrantApplication/Forms/PHS398_TrainingBudget</MessageKey> 
 		<Message>Please add a budget to the proposal.</Message> 
  		<FixLink>budgetVersions</FixLink> 
	</Error>
	<Error>
 		<MessageKey>/GrantApplication/Forms/PHS398_TrainingBudget/BudgetYear/ResearchDirectCostsRequested</MessageKey> 
 		<Message>Direct costs invalid, a stipend budget line item is required equal to or greater than the trainee numbers and associated stipend levels indicated in the questionnaire. </Message> 
  		<FixLink>budgetVersions</FixLink> 
	</Error>
	<Error>
 		<MessageKey>/GrantApplication/Forms/PHS398_TrainingBudget/BudgetYear/ResearchDirectCostsRequested</MessageKey> 
 		<Message>Direct costs invalid, a stipend budget line item is required equal to or greater than the trainee numbers and associated stipend levels indicated in the questionnaire. </Message> 
  		<FixLink>budgetVersions</FixLink> 
	</Error>
	<Error>
 		<MessageKey>/GrantApplication/Forms/PHS398_TrainingBudget/BudgetYear/TotalOtherDirectCostsRequested</MessageKey> 
 		<Message>Total Other Costs invalid, a stipend budget line item is required equal to or greater than the trainee numbers and associated stipend levels indicated in the questionnaire. </Message> 
  		<FixLink>budgetVersions</FixLink> 
	</Error>
	<Error>
 		<MessageKey>/GrantApplication/Forms/PHS398_TrainingBudget/CumulativeResearchDirectCostsRequested</MessageKey> 
 		<Message>Cumulative direct costs invalid, a stipend budget line item is required equal to or greater than the trainee numbers and associated stipend levels indicated in the questionnaire. </Message> 
  		<FixLink>budgetVersions</FixLink> 
	</Error>
	<Error>
 		<MessageKey>/GrantApplication/Forms/PHS398_TrainingBudget/CumulativeTotalOtherDirectCostsRequested</MessageKey> 
 		<Message>Cumulative other direct costs invalid, a stipend budget line item is required equal to or greater than the trainee numbers and associated stipend levels indicated in the questionnaire. </Message> 
  		<FixLink>budgetVersions</FixLink> 
	</Error>	 
	<Error>         
		<MessageKey>/GrantApplication/Forms/PHS398_TrainingBudget/BudgetJustification</MessageKey> 
   	    <Message>You must have a TrainingBudgetJustification with the proposal. Please attach the BudgetJustification in Abstracts and Attachments window</Message> 
    	<FixLink>abstractsAttachments</FixLink> 
   </Error> 
<!--	Proposal RR_Budget10 BudgetSummary validation -->

	<Error>
		  <MessageKey>/GrantApplication/Forms/RR_Budget10/BudgetSummary</MessageKey>
		  <Message>Please add a budget to the proposal.</Message>
		  <FixLink>budgetVersions</FixLink>
  	</Error> 
  	<Error>			 
		<MessageKey>/GrantApplication/Forms/RR_Budget10/BudgetJustificationAttachment</MessageKey>
		<Message>You must have a BudgetJustification with the proposal. Please attach the BudgetJustification in Abstracts and Attachments window</Message>
		<FixLink>abstractsAttachments</FixLink>
	</Error>
	<Error>			 
		<MessageKey>/GrantApplication/Forms/RR_Budget10</MessageKey>
		<Message>RR Budget10 form is not valid. Please attach the required details.</Message>
		<FixLink>abstractsAttachments</FixLink>
	</Error>
	
	<Error>
		<MessageKey>/GrantApplication/Forms/RR_FedNonFedBudget/BudgetYear1/Equipment/EquipmentList/EquipmentItem</MessageKey>
		<Message>A description is required for each Equipment budget line item.</Message>
		<FixLink>budgetVersions</FixLink>
	</Error> 
</S2SErrors>

	
	
		
	