<?xml version="1.0" encoding="UTF-8"?>
<!--
   - Kuali Coeus, a comprehensive research administration system for higher education.
   - 
   - Copyright 2005-2016 Kuali, Inc.
   - 
   - This program is free software: you can redistribute it and/or modify
   - it under the terms of the GNU Affero General Public License as
   - published by the Free Software Foundation, either version 3 of the
   - License, or (at your option) any later version.
   - 
   - This program is distributed in the hope that it will be useful,
   - but WITHOUT ANY WARRANTY; without even the implied warranty of
   - MERCHANTABILITY or FITNESS FOR A PARTICULAR PURPOSE.  See the
   - GNU Affero General Public License for more details.
   - 
   - You should have received a copy of the GNU Affero General Public License
   - along with this program.  If not, see <http://www.gnu.org/licenses/>.
 -->
<beans xmlns="http://www.springframework.org/schema/beans" xmlns:xsi="http://www.w3.org/2001/XMLSchema-instance"
       xmlns:p="http://www.springframework.org/schema/p"
       xmlns:util="http://www.springframework.org/schema/util"
       xsi:schemaLocation="http://www.springframework.org/schema/beans
                    http://www.springframework.org/schema/beans/spring-beans-3.0.xsd
                    http://www.springframework.org/schema/util
                    http://www.springframework.org/schema/util/spring-util-3.0.xsd">

    <bean id="DataValidationSection" parent="DataValidationSection-parentBean"/>
    <bean id="DataValidationSection-parentBean" parent="Uif-DialogGroup" p:resetDataOnRefresh="true"
            p:dialogCssClass="modal-lg">
        <property name="header">
            <bean parent="Uif-DialogHeader" p:headerText="Data Validation">
                <property name="rightGroup">
                    <bean parent="Uif-VerticalBoxGroup">
                        <property name="items">
                            <list>
                                <bean parent="Uif-PrimaryActionButton" p:actionLabel="@{auditActivated?'Turn Off':'Turn On'}" p:methodToCall="toggleValidation"
                                      p:refreshId="DataValidationSection"
                                      p:order="10" p:cssClasses="@{auditActivated?'btn-success':'btn-danger'}"/>
                            </list>
                        </property>
                    </bean>
                </property>
            </bean>
        </property>
        <property name="items">
            <list>
                <bean parent="DataValidationSection-Collection" p:render="@{auditActivated}" p:order="10"/>
                <bean parent="Uif-Message" p:messageText="No errors or warnings present."  p:render="@{auditActivated and dataValidationItems.size() == 0}"
                      p:order="20"/>
                <bean parent="Uif-Message" p:messageText="Data Validation is currently off."  p:render="@{!auditActivated}"
                      p:order="30"/>
            </list>
        </property>
        <property name="footer">
        	<bean parent="Uif-DialogFooter">
        		<property name="items">
                    <list>
                        <bean parent="Uif-DialogDismissButton" p:actionLabel="Close" p:order="20"/>
                    </list>
                </property>
        	</bean>
       	</property>        
    </bean>

    <bean id="DataValidationSection-Collection" parent="DataValidationSection-Collection-parentBean"/>
    <bean id="DataValidationSection-Collection-parentBean" parent="Uif-TableCollectionSection"
          p:collectionObjectClass="org.kuali.coeus.sys.impl.validation.DataValidationItem"
          p:propertyName="dataValidationItems"
          p:renderAddLine="false" p:layoutManager.renderSequenceField="false" p:readOnly="false">
        <property name="items">
            <list>
                <bean parent="Uif-DataField" p:propertyName="area" p:fieldLabel.labelText="Area" p:order="10"/>
                <bean parent="Uif-DataField" p:propertyName="section" p:fieldLabel.labelText="Section" p:order="20"/>
                <bean parent="Uif-DataField" p:propertyName="description" p:fieldLabel.labelText="Description" p:order="30"/>
                <bean parent="Uif-DataField" p:propertyName="severity" p:fieldLabel.labelText="Severity" p:order="40"
                      p:cssClasses="label,@{#ViewHelper.getErrorCssClass(#line.severity)}"/>
            </list>
        </property>
        <property name="lineActions">
            <list>
                <bean parent="Uif-ActionLink" p:actionLabel="Fix It" p:methodToCall="navigateToError"
                      p:navigateToPageId="@{#line.navigateToPageId}"
                      p:successCallback="dismissDialog('DataValidationSection');jQuery(&quot;a[id$='@{#line.navigateToSectionId}_tab']&quot;).click()"
                      p:refreshId="@{#line.navigateToPageId}"/>
            </list>
        </property>
        <property name="layoutManager.groupingPropertyNames">
            <list>
                <value>severity</value>
            </list>
        </property>
        <property name="layoutManager.richTable.templateOptions">
            <map>
                <entry key="sDom" value="tip"/>
                <entry key="bRetrieve" value="true"/>
                <entry key="bPaginate" value="false"/>
                <entry key="bInfo" value="false"/>
                <entry key="aoColumnDefs"
                       value="[{'bSortable':false, 'aTargets' : [4]}]" />
            </map>
        </property>
    </bean>

    <bean id="DataValidationSection-WithSubmit" parent="DataValidationSection-WithSubmit-parentBean"/>
    <bean id="DataValidationSection-WithSubmit-parentBean" parent="DataValidationSection">
        <property name="footer.items">
            <list>
                <bean  p:actionLabel="Submit With Warnings" parent="Uif-PrimaryActionButton" p:methodToCall="internalSubmit"  p:order="10"
                       p:render="@{#actionFlags[#Constants.KUALI_ACTION_CAN_ROUTE] and document.documentHeader.workflowDocument.saved}"
                       p:dialogDismissOption="REQUEST"/>
                <bean parent="Uif-DialogDismissButton" p:actionLabel="Close" p:order="20"/>
            </list>
        </property>
    </bean>


</beans>
